README.rst
setup.py
unicodeset.py
test/test_frozen_unicode_set.py
test/test_unicode_set.py
unicodeset.egg-info/PKG-INFO
unicodeset.egg-info/SOURCES.txt
unicodeset.egg-info/dependency_links.txt
unicodeset.egg-info/top_level.txt