Metadata-Version: 1.0
Name: unicodeset
Version: 0.1.0
Summary: set superclass for unicode character sets
Home-page: http://github.com/jackjennings/unicodeset
Author: Jack Jennings
Author-email: j@ckjennin.gs
License: LICENSE
Platform: UNKNOWN
